api/__init__.py
api/handlers.py
api/server.py
consensus/dynamic_pow.py
consensus/secure_consensus.py
core/__init__.py
core/lightweight_dag.py
core/micro_dag.py
core/consensus/__init__.py
core/consensus/conflict_detector.py
core/consensus/resolver.py
core/consensus/voter.py
core/crypto/__init__.py
core/crypto/bip39/__init__.py
core/crypto/bip39/derivation.py
core/crypto/bip39/mnemonic.py
core/crypto/blake2b/__init__.py
core/crypto/blake2b/hasher.py
core/crypto/ed25519/__init__.py
core/crypto/ed25519/compression.py
core/crypto/ed25519/keypair.py
core/crypto/ed25519/signing.py
core/genesis/__init__.py
core/genesis/genesis.py
core/processing/__init__.py
core/processing/processor.py
core/processing/receive.py
core/processing/send.py
core/types/__init__.py
core/types/account/__init__.py
core/types/account/account.py
core/types/account/encoding.py
core/types/transaction/__init__.py
core/types/transaction/builder.py
core/types/transaction/serialization.py
core/types/transaction/transaction.py
core/validation/__init__.py
core/validation/rules.py
core/validation/transaction/__init__.py
core/validation/transaction/validator.py
crypto/__init__.py
crypto/crypto_utils.py
faucet/faucet_server.py
microdag/__init__.py
microdag/cli.py
microdag/api/__init__.py
microdag/api/handlers.py
microdag/api/server.py
microdag/cli/__init__.py
microdag/cli/commands.py
microdag/cli/interface.py
microdag/consensus/__init__.py
microdag/consensus/pow.py
microdag/consensus/validator.py
microdag/core/__init__.py
microdag/core/dag.py
microdag/core/transaction.py
microdag/core/validator.py
microdag/crypto/__init__.py
microdag/crypto/keys.py
microdag/crypto/signatures.py
microdag/network/__init__.py
microdag/network/p2p.py
microdag/network/peer.py
microdag/network/protocol.py
microdag/storage/__init__.py
microdag/storage/compression.py
microdag/storage/database.py
microdag/utils/__init__.py
microdag/utils/hash.py
microdag/utils/time.py
microdag/utils/validation.py
microdag-1.0.4.dist-info/licenses/LICENSE
network/__init__.py
network/consensus.py
microdag-1.0.4.dist-info/METADATA
microdag-1.0.4.dist-info/WHEEL
microdag-1.0.4.dist-info/entry_points.txt
microdag-1.0.4.dist-info/top_level.txt
microdag-1.0.4.dist-info/RECORD
