Metadata-Version: 2.4
Name: microdag
Version: 1.0.4
Summary: Ultra-lightweight DAG blockchain optimized for IoT devices and micropayments
Home-page: https://github.com/microdag/microdag
Author: MicroDAG Team
Author-email: MicroDAG Team <team@microdag.org>
Maintainer-email: MicroDAG Team <team@microdag.org>
License: MIT
Project-URL: Homepage, https://microdag.org
Project-URL: Documentation, https://microdag.org/docs
Project-URL: Repository, https://github.com/microdag/microdag
Project-URL: Bug Reports, https://github.com/microdag/microdag/issues
Keywords: blockchain,dag,iot,micropayments,lightweight,distributed,cryptocurrency
Classifier: Development Status :: 5 - Production/Stable
Classifier: Intended Audience :: Developers
Classifier: License :: OSI Approved :: MIT License
Classifier: Operating System :: OS Independent
Classifier: Programming Language :: Python :: 3
Classifier: Programming Language :: Python :: 3.8
Classifier: Programming Language :: Python :: 3.9
Classifier: Programming Language :: Python :: 3.10
Classifier: Programming Language :: Python :: 3.11
Classifier: Programming Language :: Python :: 3.12
Classifier: Topic :: Software Development :: Libraries :: Python Modules
Classifier: Topic :: System :: Distributed Computing
Classifier: Topic :: Internet :: WWW/HTTP :: HTTP Servers
Classifier: Topic :: Database :: Database Engines/Servers
Classifier: Topic :: Security :: Cryptography
Classifier: Topic :: Office/Business :: Financial
Requires-Python: >=3.8
License-File: LICENSE
Provides-Extra: dev
Requires-Dist: pytest>=7.4.0; extra == "dev"
Requires-Dist: pytest-asyncio>=0.21.0; extra == "dev"
Requires-Dist: pytest-cov>=4.1.0; extra == "dev"
Requires-Dist: black>=23.0.0; extra == "dev"
Requires-Dist: flake8>=6.0.0; extra == "dev"
Provides-Extra: full
Requires-Dist: aiohttp>=3.8.0; extra == "full"
Requires-Dist: cryptography>=3.4.0; extra == "full"
Dynamic: author
Dynamic: home-page
Dynamic: license-file
Dynamic: requires-python
